pyxploitdb/__init__.py
pyxploitdb/exploit.py
pyxploitdb/pyxploitdb.py
pyxploitdb-2.0.dist-info/LICENSE
pyxploitdb-2.0.dist-info/METADATA
pyxploitdb-2.0.dist-info/WHEEL
pyxploitdb-2.0.dist-info/top_level.txt
pyxploitdb-2.0.dist-info/RECORD
