Metadata-Version: 2.1
Name: pyxploitdb
Version: 2.0
Summary: An exploit-db.com python API using advanced search with all possible filters.
Home-page: https://github.com/nicolasmf/pyxploit-db
Author: Nicolas MF
Author-email: nikolamf@hotmail.com
License: MIT
Project-URL: Documentation, https://github.com/nicolasmf/pyxploit-db/wiki
Keywords: api exploitdb exploit exploit-db
License-File: LICENSE
Requires-Dist: rich
